{
    "Solid" : {
        "Beef" : {
            "N" : {
                ">" : 3,
                "-" : 4,
                "<" : 5
            },
            "P" : 6,
            "K" : 10,
            "S" : 1
        },
        "Dairy: semi-solid (11.1-20.0% DM)" : {
            "N" : {
                ">" : 2,
                "-" : 2,
                "<" : 3
            },
            "P" : 3,
            "K" : 5,
            "S" : 1
        },
        "Dairy: solid (> 20.0% DM)" : {
            "N" : {
                ">" : 2,
                "-" : 3,
                "<" : 3
            },
            "P" : 3,
            "K" : 6,
            "S" : 1
        },
        "Goat" : {
            "N" : {
                ">" : 3,
                "-" : 4,
                "<" : 5
            },
            "P" : 3,
            "K" : 8,
            "S" : 1
        },
        "Horse" : {
            "N" : {
                ">" : 2,
                "-" : 3,
                "<" : 4
            },
            "P" : 5,
            "K" : 6,
            "S" : 1
        },
        "Poultry: chicken" : {
            "N" : {
                ">" : 24,
                "-" : 27,
                "<" : 29
            },
            "P" : 35,
            "K" : 26,
            "S" : 2
        },
        "Poultry: duck" : {
            "N" : {
                ">" : 6,
                "-" : 7,
                "<" : 7
            },
            "P" : 8,
            "K" : 7,
            "S" : 1
        },
        "Poultry: turkey" : {
            "N" : {
                ">" : 26,
                "-" : 28,
                "<" : 31
            },
            "P" : 35,
            "K" : 25,
            "S" : 2
        },
        "Sheep" : {
            "N" : {
                ">" : 5,
                "-" : 6,
                "<" : 7
            },
            "P" : 7,
            "K" : 19,
            "S" : 1
        },
        "Swine" : {
            "N" : {
                ">" : 7,
                "-" : 9,
                "<" : 12
            },
            "P" : 10,
            "K" : 8,
            "S" : 1
        }
    },
    "Liquid" : {
        "Beef" : {
            "N" : {
                ">" : 5,
                "-" : 6,
                "<" : 8
            },
            "P" : 6,
            "K" : 12,
            "S" : 1
        },
        "Dairy: liquid (< 4.0% DM)" : {
            "N" : {
                ">" : 4,
                "-" : 6,
                "<" : 7
            },
            "P" : 3,
            "K" : 11,
            "S" : 1
        },
        "Dairy: slurry (4.1-11.0% DM)" : {
            "N" : {
                ">" : 7,
                "-" : 10,
                "<" : 12
            },
            "P" : 6,
            "K" : 17,
            "S" : 1
        },
        "Goat" : {
            "N" : {
                ">" : 4,
                "-" : 5,
                "<" : 6
            },
            "P" : 6,
            "K" : 15,
            "S" : 1
        },
        "Poultry" : {
            "N" : {
                ">" : 6,
                "-" : 7,
                "<" : 7
            },
            "P" : 6,
            "K" : 7,
            "S" : 1
        },
        "Swine: finish (indoor pit)" : {
            "N" : {
                ">" : 17,
                "-" : 22,
                "<" : 28
            },
            "P" : 14,
            "K" : 22,
            "S" : 2
        },
        "Swine: finish (outdoor pit)" : {
            "N" : {
                ">" : 7,
                "-" : 9,
                "<" : 12
            },
            "P" : 6,
            "K" : 8,
            "S" : 1
        },
        "Swine: (farrow-nursery, indoor pit)" : {
            "N" : {
                ">" : 8,
                "-" : 10,
                "<" : 14
            },
            "P" : 6,
            "K" : 10,
            "S" : 1
        },
        "Veal calf" : {
            "N" : {
                ">" : 3,
                "-" : 4,
                "<" : 4
            },
            "P" : 2,
            "K" : 13,
            "S" : 1
        }
    }
}